ai_ensemble_suite/__init__.py
ai_ensemble_suite/ensemble.py
ai_ensemble_suite/aggregation/__init__.py
ai_ensemble_suite/aggregation/adaptive_selection.py
ai_ensemble_suite/aggregation/base.py
ai_ensemble_suite/aggregation/confidence_based.py
ai_ensemble_suite/aggregation/ensemble_fusion.py
ai_ensemble_suite/aggregation/multidimensional_voting.py
ai_ensemble_suite/aggregation/sequential_refinement.py
ai_ensemble_suite/aggregation/weighted_voting.py
ai_ensemble_suite/collaboration/__init__.py
ai_ensemble_suite/collaboration/adversarial_improvement.py
ai_ensemble_suite/collaboration/async_thinking.py
ai_ensemble_suite/collaboration/bagging.py
ai_ensemble_suite/collaboration/base.py
ai_ensemble_suite/collaboration/chain_of_thought.py
ai_ensemble_suite/collaboration/competitive_evaluation.py
ai_ensemble_suite/collaboration/expert_committee.py
ai_ensemble_suite/collaboration/hierarchical_review.py
ai_ensemble_suite/collaboration/integration.py
ai_ensemble_suite/collaboration/perspective_rotation.py
ai_ensemble_suite/collaboration/role_based_workflow.py
ai_ensemble_suite/collaboration/stackedgeneralization.py
ai_ensemble_suite/collaboration/uncertaintybased.py
ai_ensemble_suite/collaboration/structured_debate/__init__.py
ai_ensemble_suite/collaboration/structured_debate/base_debate.py
ai_ensemble_suite/collaboration/structured_debate/critique.py
ai_ensemble_suite/collaboration/structured_debate/role_based.py
ai_ensemble_suite/collaboration/structured_debate/synthesis.py
ai_ensemble_suite/config/__init__.py
ai_ensemble_suite/config/config_manager.py
ai_ensemble_suite/config/defaults.py
ai_ensemble_suite/config/schema.py
ai_ensemble_suite/config/template_manager.py
ai_ensemble_suite/config/templates.py
ai_ensemble_suite/exceptions/__init__.py
ai_ensemble_suite/exceptions/exceptions.py
ai_ensemble_suite/models/__init__.py
ai_ensemble_suite/models/confidence.py
ai_ensemble_suite/models/gguf_model.py
ai_ensemble_suite/models/model_manager.py
ai_ensemble_suite/utils/__init__.py
ai_ensemble_suite-0.5.1.dist-info/licenses/LICENSE
ai_ensemble_suite-0.5.1.dist-info/METADATA
ai_ensemble_suite-0.5.1.dist-info/WHEEL
ai_ensemble_suite-0.5.1.dist-info/top_level.txt
ai_ensemble_suite-0.5.1.dist-info/RECORD
