Metadata-Version: 2.4
Name: ai-ensemble-suite
Version: 0.5.1
Summary: Python framework for multiple GGUF language models to collaborate on tasks
Author-email: Stephen Genusa <github@genusa.com>
License-Expression: MIT
Project-URL: Homepage, https://github.com/StephenGenusa/ai-ensemble-suite
Project-URL: Bug Tracker, https://github.com/StephenGenusa/ai-ensemble-suite/issues
Project-URL: Documentation, https://stephengenusa.github.io/ai-ensemble-suite
Keywords: llm,ai,ensemble,language-model,gguf,llama,ai-ensemble
Classifier: Development Status :: 3 - Alpha
Classifier: Intended Audience :: Developers
Classifier: Programming Language :: Python :: 3
Classifier: Programming Language :: Python :: 3.10
Classifier: Programming Language :: Python :: 3.11
Classifier: Programming Language :: Python :: 3.12
Classifier: Topic :: Scientific/Engineering :: Artificial Intelligence
Requires-Python: >=3.10
License-File: LICENSE
Requires-Dist: llama-cpp-python
Requires-Dist: pyyaml
Requires-Dist: colorama
Requires-Dist: Jinja2
Requires-Dist: psutil
Provides-Extra: dev
Requires-Dist: pytest>=7.0.0; extra == "dev"
Requires-Dist: pytest-asyncio>=0.20.0; extra == "dev"
Requires-Dist: pytest-cov>=4.0.0; extra == "dev"
Requires-Dist: black>=23.0.0; extra == "dev"
Requires-Dist: flake8>=6.0.0; extra == "dev"
Requires-Dist: mypy>=1.0.0; extra == "dev"
Requires-Dist: tox>=4.0.0; extra == "dev"
Requires-Dist: mkdocs>=1.4.0; extra == "dev"
Requires-Dist: mkdocs-material>=8.5.0; extra == "dev"
Requires-Dist: mkdocstrings>=0.19.0; extra == "dev"
Requires-Dist: mkdocstrings-python>=0.8.0; extra == "dev"
Provides-Extra: rich
Requires-Dist: rich>=12.0.0; extra == "rich"
Dynamic: license-file
